{
  "problemId": 32278,
  "titleKo": "\uc120\ud0dd \uac00\ub2a5\uc131\uc774 \uac00\uc7a5 \ub192\uc740 \uc790\ub8cc\ud615",
  "titles": [
    {
      "language": "ko",
      "languageDisplayName": "ko",
      "title": "\uc120\ud0dd \uac00\ub2a5\uc131\uc774 \uac00\uc7a5 \ub192\uc740 \uc790\ub8cc\ud615",
      "isOriginal": true
    }
  ],
  "isSolvable": true,
  "isPartial": false,
  "acceptedUserCount": 1194,
  "level": 2,
  "votedUserCount": 55,
  "sprout": false,
  "givesNoRating": false,
  "isLevelLocked": false,
  "averageTries": 1.4355,
  "official": true,
  "tags": [
    {
      "key": "implementation",
      "isMeta": false,
      "bojTagId": 102,
      "problemCount": 6676,
      "displayNames": [
        {
          "language": "ko",
          "name": "\uad6c\ud604",
          "short": "\uad6c\ud604"
        },
        {
          "language": "en",
          "name": "implementation",
          "short": "impl"
        },
        {
          "language": "ja",
          "name": "\u5b9f\u88c5",
          "short": "impl"
        }
      ],
      "aliases": []
    }
  ],
  "metadata": {}
}